salt_packets/__init__.py
salt_packets/main.py
salt_packets/controllers/__init__.py
salt_packets/controllers/base.py
salt_packets/core/__init__.py
salt_packets/core/exc.py
salt_packets/core/version.py
salt_packets/ext/__init__.py
salt_packets/plugins/__init__.py
salt_packets-0.2.6b4.dist-info/LICENSE.md
salt_packets-0.2.6b4.dist-info/METADATA
salt_packets-0.2.6b4.dist-info/WHEEL
salt_packets-0.2.6b4.dist-info/entry_points.txt
salt_packets-0.2.6b4.dist-info/top_level.txt
salt_packets-0.2.6b4.dist-info/RECORD
