Metadata-Version: 2.1
Name: salt-packets
Version: 0.2.6b4
Summary: portable, reusable, self-managed salt projects
Home-page: https://code.netprophet.tech/netp/salt-packets
Author: Leeward Bound
Author-email: lee@netprophet.tech
License: unlicensed
Platform: UNKNOWN
Requires-Dist: cement (==3.0.4)
Requires-Dist: jinja2
Requires-Dist: pyyaml
Requires-Dist: colorlog
Requires-Dist: colored
Requires-Dist: pyfiglet
Requires-Dist: python-dotenv
Requires-Dist: influxdb
